oarepo_model_builder_vocabularies/__init__.py
oarepo_model_builder_vocabularies/components.py
oarepo_model_builder_vocabularies/datatypes.py
oarepo_model_builder_vocabularies/builders/__init__.py
oarepo_model_builder_vocabularies/builders/setup_cfg.py
oarepo_model_builder_vocabularies/models/__init__.py
oarepo_model_builder_vocabularies/models/vocabulary.json
oarepo_model_builder_vocabularies/models/vocabulary.yaml
oarepo_model_builder_vocabularies-4.0.10.dist-info/METADATA
oarepo_model_builder_vocabularies-4.0.10.dist-info/WHEEL
oarepo_model_builder_vocabularies-4.0.10.dist-info/entry_points.txt
oarepo_model_builder_vocabularies-4.0.10.dist-info/top_level.txt
oarepo_model_builder_vocabularies-4.0.10.dist-info/RECORD
