Metadata-Version: 2.4
Name: oarepo-model-builder-vocabularies
Version: 4.0.10
Summary: "A model builder plugin to reference vocabularies"
Home-page: https://github.com/oarepo/oarepo-model-builder-vocabularies
Author: Miroslav Simek
Author-email: simek.miroslav@techlib.cz
License: MIT
Keywords: invenio vocabulary model builder
Platform: any
Classifier: Development Status :: 3 - Alpha
Requires-Python: >=3.9
Requires-Dist: oarepo-model-builder>=4.0.0
Requires-Dist: oarepo-model-builder-relations>=4.0.0
Requires-Dist: oarepo-model-builder-cf>=4.0.0
Requires-Dist: oarepo-model-builder-ui>=4.0.0
Provides-Extra: tests
Requires-Dist: pytest; extra == "tests"
